s_swampy-0.2.2.dist-info/DESCRIPTION.rst
s_swampy-0.2.2.dist-info/METADATA
s_swampy-0.2.2.dist-info/RECORD
s_swampy-0.2.2.dist-info/WHEEL
s_swampy-0.2.2.dist-info/metadata.json
s_swampy-0.2.2.dist-info/top_level.txt
swampy/sen2coral/__init__.py
swampy/sen2coral/define_outputs.py
swampy/sen2coral/sambuca_calculations.py
swampy/sen2coral/sambuca_input_parameters.py
swampy/sen2coral/sambuca_input_rrs.py
swampy/sen2coral/sambuca_outputs.py
swampy/sen2coral/sambuca_preparation.py
