Metadata-Version: 2.0
Name: s-swampy
Version: 0.2.2
Summary: SWAMpy model
Home-page: UNKNOWN
Author: Stephen Sagar
Author-email: stephen.sagar@ga.gov.au
License: Unknown
Keywords: Hydrology Modeling Bathymetry
Platform: any
Classifier: Development Status :: 3 - Alpha
Classifier: Intended Audience :: Science/Research
Classifier: Programming Language :: Python :: 3
Requires-Dist: s-sambuca-core (==1.2.4)
Requires-Dist: s-sambuca (==0.3.1)
